diffevo/__init__.py
diffevo/ddim.py
diffevo/examples.py
diffevo/fitnessmapping.py
diffevo/generator.py
diffevo/kde.py
diffevo/latent.py
diffevo/optimizer.py
diffevo-1.1.0.dist-info/LICENSE
diffevo-1.1.0.dist-info/METADATA
diffevo-1.1.0.dist-info/WHEEL
diffevo-1.1.0.dist-info/top_level.txt
diffevo-1.1.0.dist-info/RECORD
