Metadata-Version: 2.1
Name: diffevo
Version: 1.1.0
Summary: Diffusion Evolutionary Algorithm
Home-page: https://github.com/Zhangyanbo/diffusion-evolution
Author: Yanbo Zhang
Author-email: zhangybspm@gmail.com
Project-URL: Bug Tracker, https://github.com/Zhangyanbo/diffusion-evolution/issues
Classifier: Programming Language :: Python :: 3
Classifier: License :: Other/Proprietary License
Classifier: Operating System :: OS Independent
Requires-Python: >=3.6
License-File: LICENSE
